{
    "platform": "大麦",
    "project_id": "791870283537",
    "project_name": "「零点之后」520欢唱派对（福州）",
    "category_name": "演唱会",
    "artists": [],
    "show_status": "售票中",
    "show_time": "2024.05.20 周一 20:00",
    "session_time": [
        "05.20 周一"
    ],
    "price": "68-158",
    "isGeneralAgent": "true",
    "isHotProject": "false",
    "rating": null,
    "city_name": "福州",
    "venue_name": "MoliLive茉莉空间",
    "venue_info": {
        "venue_address": "东岭路333号福湾路海峡奥体中心网球中心W1-1馆",
        "lng": 119.285889,
        "lat": 26.020596
    },
    "project_info": "【福州】5.20「零点之后」欢唱派对",
    "project_imgs": [
        "https://img.alicdn.com/bao/uploaded/https://img.alicdn.com/imgextra/i3/2251059038/O1CN01NdLymJ2GdSb82Eh9C_!!2251059038.png",
        "https://img.alicdn.com/imgextra/i4/2251059038/O1CN01VOztXw2GdSb0LgAfA_!!2251059038.jpg",
        "https://img.alicdn.com/imgextra/i4/2251059038/O1CN01GRC5cn2GdSb6ApF61_!!2251059038.jpg",
        "https://img.alicdn.com/imgextra/i1/2251059038/O1CN019nsXii2GdSb9LCM1q_!!2251059038.jpg",
        "https://img.alicdn.com/imgextra/i1/2251059038/O1CN01c6Y8Mz2GdSb9md0OQ_!!2251059038.jpg",
        "https://img.alicdn.com/imgextra/i4/2251059038/O1CN010zIlUF2GdSbAzPqxj_!!2251059038.jpg",
        "https://img.alicdn.com/imgextra/i2/2251059038/O1CN01LlrsRx2GdSb0LjOOM_!!2251059038.jpg",
        "https://img.alicdn.com/imgextra/i4/2251059038/O1CN012yhPBb2GdSb9LFJ5P_!!2251059038.jpg",
        "https://img.alicdn.com/imgextra/i2/2251059038/O1CN01spNLpA2GdSb9mfQCD_!!2251059038.jpg",
        "https://img.alicdn.com/imgextra/i2/2251059038/O1CN01X3paF52GdSb82JfGd_!!2251059038.jpg",
        "https://img.alicdn.com/imgextra/i4/2251059038/O1CN01MbMB5k2GdSb7lmSQC_!!2251059038.jpg"
    ],
    "wantVO": {
        "wantNum": null,
        "wantNumStr": null,
        "wantNumSuffix": null,
        "wantDesc": null
    },
    "tours": [],
    "project_link": "https://detail.damai.cn/item.htm?id=791870283537"
}