{
    "platform": "大麦",
    "project_id": "795963081496",
    "project_name": "ALexandr Misko 2024 《进化时间》指弹吉他音乐会 厦门站",
    "category_name": "演唱会",
    "artists": [],
    "show_status": "售票中",
    "show_time": "2024.07.16 周二 20:00",
    "session_time": [
        "07.16 周二"
    ],
    "price": "240-380",
    "isGeneralAgent": "false",
    "isHotProject": "false",
    "rating": null,
    "city_name": "厦门",
    "venue_name": "RealLive And Books",
    "venue_info": {
        "venue_address": "厦门市湖里区联发东南天地文化创意产业园C106",
        "lng": 118.097185,
        "lat": 24.512446
    },
    "project_info": "",
    "project_imgs": [
        "https://img.alicdn.com/bao/uploaded/https://img.alicdn.com/imgextra/i2/2251059038/O1CN01ajWcWU2GdSbE31KlL_!!2251059038.png",
        "https://img.alicdn.com/imgextra/i4/2251059038/O1CN018B2Edc2GdSbBXzhQM_!!2251059038.jpg"
    ],
    "wantVO": {
        "wantNum": null,
        "wantNumStr": null,
        "wantNumSuffix": null,
        "wantDesc": null
    },
    "tours": [],
    "project_link": "https://detail.damai.cn/item.htm?id=795963081496"
}