{
    "platform": "大麦",
    "project_id": "797181200967",
    "project_name": "上海｜5.25 国民级“回忆杀”《音乐之声》爵士乐专场，感动你的回忆",
    "category_name": "演唱会",
    "artists": [],
    "show_status": "售票中",
    "show_time": "2024.05.25 周六 20:00",
    "session_time": [
        "05.25 周六"
    ],
    "price": "180",
    "isGeneralAgent": "true",
    "isHotProject": "false",
    "rating": null,
    "city_name": "上海",
    "venue_name": "Blue Note Shanghai",
    "venue_info": {
        "venue_address": "上海市虹口区四川北路867号中信广场3-5层",
        "lng": 121.484046,
        "lat": 31.248428
    },
    "project_info": "\n是否曾有过这样一个瞬间，一段旋律忽然在脑海中响起，勾起心底深处最柔软的记忆？\n1965年，整个世界沉浸在战后时代对和平、自由与爱的向往和呼唤里，罗伯特·怀斯导了一部《音乐之声》带领人们走进了阿尔卑斯山脚下最纯净的土地，讲述了一个关于勇气与爱的传奇。\n\n在那个动荡不安的年代，这部电影给无数人带来了温暖与希望，往后的岁月里这样的美好代代相传，成为国民级回忆。\n5月25日·Blue Note Shanghai\n现场感受《音乐之声》这部电影带来的诸多美好\n我们不见不散！\n\n美好ONE\n旋律中的童真与美好\nDo-Re-Mi & My Favorite Things\n\n影片中，妙龄修女玛丽亚来到特拉普上校家中，成为家庭教师。\n当她抱着吉他、带着七个孩子雀跃在蓝天白云绿地间，教孩子们用音符记忆旋律时，背景中和穆的阿尔卑斯山脉仿佛也在安静地聆听《Do-Re-Mi》轻快的声响。\n爵士乐的自由与随性，完美地诠释了这首歌带来的纯粹快乐，我们必将被这节奏滋养和拯救。\n玛丽亚还告诉孩子们：烦心的时候，就想自己喜欢的事物愉悦自己。\n\n《My Favorite Things》一样能够唤起我们对美好事物的热爱，每一个音符都像是对生活的小小礼赞。\n来现场听，唤起的美好一定是双倍滴！！！\n\n美好TWO\n深情地告白与梦想\nEdelweiss & The Sound of Music\n军官音乐会上，上校对众人说要唱首情歌，于是他弹着吉他唱起了奥地利民歌《Edelweiss》（雪绒花），此时的他正决定要离开家乡。\n\n雪绒花是一种阿尔卑斯山上的植物，“小而白，洁又亮”，《Edelweiss》那对故土的深情告白，都将化为漫长余生的怀念。\n来现场，听这封写给家乡的音乐情书。\n \n美好THREE\n攀登心灵的高峰\nClimb Ev'ry Mountain\n玛丽亚从上校家回到修道院，修女长见她心情沮丧，便唱响了《Climb Ev'ry Mountain》，鼓励玛丽亚追寻梦想，就像攀越群山。\n\n“这些墙不是为了挡住你的问题，你要正视它，要按照你的生活道路去生活。攀登每一座山，不论高低皆要寻求；踏遍每条偏僻的小路，你都必须走；攀登每一座山，涉过小溪，追寻每一道彩虹，直到找到你的梦想。这梦想需要你献出全部的爱，在你有生之日一直走下去。”\n——院长嬷嬷\n攀越群山鼓励片中的玛利亚，也鼓励我们每一个人要勇攀高峰，追寻心灵的高度。\n\n不管你是忠实的《音乐之声》电影迷，还是爵士乐爱好者，这个专场绝对是无与伦比的听觉盛宴。\n25日晚一定要来！让我们一同走进《音乐之声》的世界，用爵士的方式重新诠释那些动人的旋律，感受万物之美。\n\n\n\nBass - Danny Zander\nTrumpet - Toby Mak\nSax - Mike Hirsch\nPiano - 彭俊达\nDrums - Pascal Naigom\n\nBass - Danny Zander\nDanny Zanker，一名来自美国的贝斯手。年少刚接触音乐时，起初只是想试探自己的兴趣在哪里，当时哥哥和几乎身边所有的朋友都选择了学习弹吉他，而Danny却觉得学贝斯能更快地融入乐队。后来事实证明他对贝斯有着神奇的天赋，两年之后他就已经开始进行专业的表演了。最终，出于对爵士乐的喜爱他选择了低音贝斯并且搬去纽约生活，去接触世界各地的音乐人们。他带着15年在纽约爵士演奏的丰富经验，Danny Zanker于2009年来到中国，开始了在上海的新鲜生活。从那时起，他和几个知名乐队合作表演，其中包括李晓川乐队，赵可·能性，陈胤希和她的爵士先生们等等。同时他也成功地组建了自己的乐队－ZankinFives，并经常在爵士大师的中国巡演中有出色的表现。\n\nTrumpet - Toby Mak\nToby Mak是中国乃至亚洲最受欢迎的爵士小号演奏家之一，他以极富情感、深邃优雅的精湛小号演奏技艺闻名于中国爵士乐界。\n其原创爵士五重奏专辑《07印象》曾荣获第28届JZ Awards华人爵士大奖“最佳专辑奖”，并提名2017台湾金曲奖“最佳专辑奖”。合作过莫文蔚、方大同、李荣浩、Dee Dee Bridgewater、Chris Potter、Tina May等海内外音乐人。\n\nSax - Mike Hirsch\nMike Hirsch出生并成长于美国波士顿，在八岁时开始了爵士萨克斯风的学习与演奏。他高中时师从著名爵士乐艺术家、教育家Jerry Bergonzi，收到过伯克利音乐学院和新英格兰音乐学院的入学奖学金。Mike毕业于斯坦福大学，曾在斯坦福爵士工作室担任教师。他曾与Wynton Marsalis, Jerry Bergonzi, Jon Faddis, Louis Bellson, Dee Dee Bridgewater, Jon Nemeth等著名音乐家在北美和欧洲的重要音乐场所合作演出。目前Mike与他的家人在上海和洛杉矶两地居住。\n\n\nPiano - 彭俊达\nPizzicato音乐咨询工作室创始人，师从爵士钢琴先驱白天、黄健怡、著名音乐作曲家纪冬泳。演出足迹遍布林肯爵士乐上海中心、Beijing Blue note、Shanghai Blue note、JZ Club、草莓音乐节、夏至爵士音乐节、当代艺术文化周、崇明岛艺术周《瀛洲琴韵同心守沪》等知名爵士演出场馆和音乐节。其个人组建的五重奏、四重奏、三重奏乐队曾多次巡演于武汉琴台剧院、江西省文化大剧院、上海歌剧院、德州艺术中心等。2018年参与演奏交响诗《创世纪》。筹划参与东方卫视《雨和泪公益主题活动》。曾在优酷、牛班从事音乐编写、制作、制谱活动，其中有大型动漫连续剧，游戏配乐等等。2021年威雅文化节，指导作品E Phrygian War在悲惨世界指挥Richard Ward Roden指挥下进行首演，也是唯一亚洲高校入围决赛作品。2023年制作上戏毕业剧《三姐妹》配乐、传统中国儿歌作曲，并荣获Universal Start competition作曲金奖指导老师。\n\nDrums - Pascal Naigom\n毛里求斯籍爵士鼓演奏家，七岁开始学习打击乐，13岁开始在教堂演出。在毕业于Francois Mitterand 音乐学院之后，Pascal在2003年组建了自己的乐队，乐队的演出足迹遍布毛里求斯各大顶级演出场所。\n\n2024年5月25日（周六）\n入场时间/Door Time：18:30\n演出时间/Show Time：20:00\n地址/Add：\n上海市虹口区四川北路867号中信广场3层\n（入口位于四川北路沿街，商场电梯直达）\nAdd. 3F, CITIC Plaza, No. 867 North Sichuan Road, Hongkou District, Shanghai.\n(The entrance is located along North Sichuan Road\nand can be directly accessed via the mall elevator)\n\n预售 ¥180\n现场 ¥220\n\n1. 所有网上购票观众请携带购票二维码到前台换取当日演出门票，凭票入场。门票一经出售，概不退换；\n2. 现场座位采取\"先到先得\"的方式，为能准时进场，请提前预留换票时间；\n3. 观众凭前台换取的桌卡进入演出场地，由服务人员引领至相应座位入座；\n4. 因场地座位有限，会有拼桌现象，敬请谅解；\n5. 儿童入场须家长陪同，请家长善尽监护义务，禁止儿童在观众席内嬉闹，以免影响其他客人；\n6. Blue Note Shanghai提供餐饮服务，入场后即可点餐。谢绝自带食品与酒水进入场地；\n7. 门票发票须演出当日凭桌卡开具；\n",
    "project_imgs": [
        "https://img.alicdn.com/bao/uploaded/i2/2251059038/O1CN01iqH7Yx2GdSbFnNa8C_!!2-item_pic.png",
        "https://img.alicdn.com/imgextra/i1/2251059038/O1CN01pxr5DO2GdSbIWAWtq_!!2251059038.png",
        "https://img.alicdn.com/imgextra/i1/2251059038/O1CN015s3H5N2GdSbHmMwfN_!!2251059038.png",
        "https://img.alicdn.com/imgextra/i1/2251059038/O1CN01aVuLjW2GdSb7BqeHh_!!2251059038.png",
        "https://img.alicdn.com/imgextra/i3/2251059038/O1CN01kWMVoe2GdSbG8OcJp_!!2251059038.png",
        "https://img.alicdn.com/imgextra/i2/2251059038/O1CN01eEJpia2GdSbCdMe3a_!!2251059038.png",
        "https://img.alicdn.com/imgextra/i3/2251059038/O1CN010Z1Aez2GdSbJ8NRLd_!!2251059038.png",
        "https://img.alicdn.com/imgextra/i2/2251059038/O1CN01Q7So5s2GdSbHmNHUG_!!2251059038.png",
        "https://img.alicdn.com/imgextra/i1/2251059038/O1CN01wAD4wk2GdSbGakSvJ_!!2251059038.png",
        "https://img.alicdn.com/imgextra/i4/2251059038/O1CN01F5691M2GdSbCzooVO_!!2251059038.png",
        "https://img.alicdn.com/imgextra/i4/2251059038/O1CN01Omow4F2GdSbCdMJ3K_!!2251059038.png",
        "https://img.alicdn.com/imgextra/i1/2251059038/O1CN01G3mse02GdSbIWEHxJ_!!2251059038.png",
        "https://img.alicdn.com/imgextra/i3/2251059038/O1CN019F2nZH2GdSbEbZydG_!!2251059038.png",
        "https://img.alicdn.com/imgextra/i3/2251059038/O1CN01p5Jht42GdSbIWD0vo_!!2251059038.png",
        "https://img.alicdn.com/imgextra/i1/2251059038/O1CN010xaF572GdSbFHmxLQ_!!2251059038.png",
        "https://img.alicdn.com/imgextra/i2/2251059038/O1CN01J5gBuJ2GdSbBjqKFv_!!2251059038.png",
        "https://img.alicdn.com/imgextra/i1/2251059038/O1CN01j26bQ42GdSbGhO8Vp_!!2251059038.png",
        "https://img.alicdn.com/imgextra/i1/2251059038/O1CN01GQEUK32GdSbCdLEY5_!!2251059038.png",
        "https://img.alicdn.com/imgextra/i3/2251059038/O1CN01JEXALK2GdSbCzqYcI_!!2251059038.png"
    ],
    "wantVO": {
        "wantNum": null,
        "wantNumStr": null,
        "wantNumSuffix": null,
        "wantDesc": null
    },
    "tours": [],
    "project_link": "https://detail.damai.cn/item.htm?id=797181200967"
}