{
    "platform": "大麦",
    "project_id": "815861406657",
    "project_name": "OB03 2024 新专辑巡演 「Platinum Tour」",
    "category_name": "演唱会",
    "artists": [
        "OB03"
    ],
    "show_status": "售票中",
    "show_time": "2024.09.17 周二 20:00",
    "session_time": [],
    "price": "99-209",
    "isGeneralAgent": "true",
    "isHotProject": "false",
    "rating": null,
    "city_name": "上海",
    "venue_name": "MAO Livehouse上海",
    "venue_info": {
        "venue_address": "重庆南路308号3F(近建国中路)",
        "lng": 121.472096,
        "lat": 31.209894
    },
    "project_info": "OB03全新专辑巡演:在现场与《弗兰肯斯坦（DUET）》共鸣\n      “OB03即将开启他们的全新巡演，带你进入一个与黑暗中的怪物对话的音乐世界，让它们的自白成为音符，让它们的发问成为旋律。”\n      2023年年底，OB03发布组合的第三张专辑《弗兰肯斯坦（DUET）》，又在年初发组合EP 《白金Club》，高产且高质量的产出，让OB03将通过巡演带来更加高能量的音乐，通过现场展现矛盾、疯狂、纯真与痛苦。\n 巡演日程：\n07/20（周六）｜杭州 MAO LiveHouse \n08/17（周六） ｜福州 唯美客MAKERLIVE（i33）\n09/17（周二） ｜上海 MAO LiveHouse票务信息 ：\n学生票 ￥99\n预售票 ￥179\n现场票 ￥209\n*本次现场设专辑签售，观众可根据需求现场购买参与签售～\n*演出当天请购买学生票的同学携带【学生证件或相关证明】排队检票哦！\n*切勿购买黄牛票，避免造成财产损失！\n \n       OB03的全新巡演将带你进入一个由《弗兰肯斯坦（DUET）》打造的情感迷宫，呈现专辑歌曲。\n      巡演将探索内在的孤独与扭曲。与对爱的不同探寻，描绘出梦境崩塌和情绪抑制，象征整个故事的决定性结局。\n      距离OB03上一次正式巡演已过一年，这一次他们积蓄了更多力量和灵感。此次巡演不仅是对新专辑的呈现，更是OB03音乐旅程的新起点。\n在OB03的现场中，唤醒内心深处的怪物，直面、解脱、成长。\n \n ",
    "project_imgs": [
        "https://img.alicdn.com/bao/uploaded/https://img.alicdn.com/imgextra/i1/2251059038/O1CN01OUoyNo2GdSc6aWcUA_!!2251059038.png",
        "https://img.alicdn.com/imgextra/i1/2251059038/O1CN01V3cseG2GdScAzM2Dl_!!2251059038.jpg",
        "https://img.alicdn.com/imgextra/i2/2251059038/O1CN01MctuFL2GdSbrKVy1V_!!2251059038.jpg",
        "https://img.alicdn.com/imgextra/i3/2251059038/O1CN01Q7P6HK2GdSbp9eUlJ_!!2251059038.jpg"
    ],
    "wantVO": {
        "wantNum": null,
        "wantNumStr": null,
        "wantNumSuffix": "人",
        "wantDesc": null
    },
    "tours": [
        {
            "itemId": "815861406657",
            "cityName": "上海站",
            "showTime": "09.17"
        },
        {
            "itemId": "809728488544",
            "cityName": "杭州站",
            "showTime": "07.20"
        },
        {
            "itemId": "810159372570",
            "cityName": "福州站",
            "showTime": "08.17"
        }
    ],
    "project_link": "https://detail.damai.cn/item.htm?id=815861406657"
}