{
    "platform": "大麦",
    "project_id": "826585448676",
    "project_name": "Ella陈嘉桦「BAD HABITS」新专音乐会·武汉站",
    "category_name": "演唱会",
    "artists": [
        "Ella陈嘉桦"
    ],
    "show_status": "售票中",
    "show_time": "2024.09.07 周六 19:30",
    "session_time": [],
    "price": "480",
    "isGeneralAgent": "false",
    "isHotProject": "false",
    "rating": null,
    "city_name": "武汉",
    "venue_name": "不晚IN TIME LIVE",
    "venue_info": {
        "venue_address": "武汉市汉阳区汉阳造文化创意园46栋",
        "lng": 114.26832,
        "lat": 30.557467
    },
    "project_info": "",
    "project_imgs": [
        "https://img.alicdn.com/bao/uploaded/i4/2251059038/O1CN01Kg9TyA2GdScon0h1B_!!2-item_pic.png",
        "https://img.alicdn.com/imgextra/i4/2251059038/O1CN019n0W7h2GdScrKxfqX_!!2251059038.jpg"
    ],
    "wantVO": {
        "wantNum": "857",
        "wantNumStr": "857",
        "wantNumSuffix": "人",
        "wantDesc": null
    },
    "tours": [],
    "project_link": "https://detail.damai.cn/item.htm?id=826585448676"
}