{
    "platform": "大麦",
    "project_id": "836588904482",
    "project_name": "【全场畅饮】PARTY CN「囍」狂欢派对",
    "category_name": "演唱会",
    "artists": [],
    "show_status": "售票中",
    "show_time": "2024.10.26 周六 19:30",
    "session_time": [],
    "price": "88-198",
    "isGeneralAgent": "true",
    "isHotProject": "false",
    "rating": null,
    "city_name": "北京",
    "venue_name": "IMAGINE 想象空间",
    "venue_info": {
        "venue_address": "北京市海淀区学清路38号BOM嘻番里305",
        "lng": 116.353777,
        "lat": 40.001783
    },
    "project_info": "【全场畅饮】PARTY CN「囍」狂欢派对\n",
    "project_imgs": [
        "https://img.alicdn.com/bao/uploaded/i1/2251059038/O1CN01Mss9ZR2GdSdNR39cX_!!2-item_pic.png",
        "https://img.alicdn.com/imgextra/i1/2251059038/O1CN01t4Vzi52GdSdLx9zL0_!!2251059038.jpg"
    ],
    "wantVO": {
        "wantNum": null,
        "wantNumStr": null,
        "wantNumSuffix": "人",
        "wantDesc": null
    },
    "tours": [],
    "project_link": "https://detail.damai.cn/item.htm?id=836588904482"
}