{
    "platform": "大麦",
    "project_id": "841825907499",
    "project_name": "Hi！Halloween万圣联合专场",
    "category_name": "演唱会",
    "artists": [],
    "show_status": "售票中",
    "show_time": "2024.11.01 周五 19:00",
    "session_time": [],
    "price": "198-298",
    "isGeneralAgent": "true",
    "isHotProject": "false",
    "rating": null,
    "city_name": "哈尔滨",
    "venue_name": "原料库 Vast Factory(会展店)",
    "venue_info": {
        "venue_address": "哈尔滨市南岗区黄河路200号会展中心体育馆南门旁",
        "lng": 126.706481,
        "lat": 45.755033
    },
    "project_info": "Hi！Halloween万圣联合专场\n",
    "project_imgs": [
        "https://img.alicdn.com/bao/uploaded/i2/2251059038/O1CN01YGg9B02GdSdmKcMuZ_!!2-item_pic.png",
        "https://img.alicdn.com/imgextra/i1/2251059038/O1CN01AbXRBp2GdSdiUQyzv_!!2251059038.jpg"
    ],
    "wantVO": {
        "wantNum": "1154",
        "wantNumStr": "1154",
        "wantNumSuffix": "人",
        "wantDesc": null
    },
    "tours": [],
    "project_link": "https://detail.damai.cn/item.htm?id=841825907499"
}