{
    "platform": "大麦",
    "project_id": "873784295366",
    "project_name": "NIKI: Buzz World Tour in Hong Kong",
    "category_name": "演唱会",
    "artists": [],
    "show_status": "售票中",
    "show_time": "2025.02.09 周日 20:00",
    "session_time": [
        "02.09 周日"
    ],
    "price": "599-1899",
    "isGeneralAgent": "false",
    "isHotProject": "false",
    "rating": null,
    "city_name": "中国香港",
    "venue_name": "亚洲国际博览馆 Hall 5",
    "venue_info": {
        "venue_address": "位处香港国际机场附近",
        "lng": 113.948164,
        "lat": 22.318327
    },
    "project_info": "日期: 2025月2月9日时间：晚上20:00地点: 亚洲国际博览馆5号展馆\n \n购票说明：本项目门票不支持退换，不可转让。此项目不设坐席，仅设站席，凭门票序号进场。儿童一律凭票入场，身高140cm以下和12岁以下不可入场，入场时必需持有有效门票，不建议孕妇购票入场。购票成功的客户，请您提前办理好港澳通行证-中国香港签注。演出当天凭大麦APP/小程序的购票二维码，到指定换票点换取纸质票后检票入场。当天如出现遗失或忘带门票情况不予处理，感谢您的支持与理解。1. 取票点：场馆售票亭2. 取票时间：活动当天请合理安排出行时间以免耽误观演，祝您观演愉快！\n \n门票价格：港币票价HKD： HK$1899/$1399/$899/¥599人民币售价CNY： 1899元/1399元/899元/599元*门票已含境外（含港澳台）服务费\n \nULTIMATE VIP PACKAGE | HKD 1,899▹ HKD 899门票一张▹ 优先入场安排（首批入场）▹ 获邀请参与NIKI演前Soundcheck▹ VIP专属NIKI印刷签名歌词手稿一张▹ 纪念卡牌及颈绳▹ VIP专属特别设计礼品▹ 优先购买官方周边商品\n \nPREMIUM VIP PACKAGE | HKD 1,399▹ HKD 899门票一张▹ 优先入场安排（第二批入场）▹ VIP专属NIKI印刷歌词手稿一张▹ 纪念卡牌及颈绳▹ VIP专属特别设计礼品▹ 优先购买官方周边商品\n \n演出介绍：88Rising 旗下唱作女歌手NIKI 的世界巡演即将登陆香港！这次是NIKI首度来港开唱，到底会为香港歌迷带来什么样惊喜？ 约定你们2月一起来亚博欣赏NIKI的演出！\n\n \n\n \n",
    "project_imgs": [
        "https://img.alicdn.com/bao/uploaded/https://img.alicdn.com/imgextra/i4/2251059038/O1CN01UYuwTv2GdSfapOkiN_!!2251059038.jpg",
        "https://img.alicdn.com/imgextra/i3/2251059038/O1CN018nVcnA2GdSfVzdY8e_!!2251059038.png",
        "https://img.alicdn.com/imgextra/i3/2251059038/O1CN01ENNdHw2GdSfY7r8wA_!!2251059038.png",
        "https://img.alicdn.com/imgextra/i2/2251059038/O1CN01Zg2yCc2GdSfVzf5q8_!!2251059038.png"
    ],
    "wantVO": {
        "wantNum": null,
        "wantNumStr": null,
        "wantNumSuffix": null,
        "wantDesc": null
    },
    "tours": [],
    "project_link": "https://detail.damai.cn/item.htm?id=873784295366"
}