{
    "platform": "大麦",
    "project_id": "884641392953",
    "project_name": "2.13 Seasons of Love",
    "category_name": "演唱会",
    "artists": [],
    "show_status": "售票中",
    "show_time": "2025.02.13 周四 19:30",
    "session_time": [],
    "price": "168-388",
    "isGeneralAgent": "true",
    "isHotProject": "false",
    "rating": null,
    "city_name": "上海",
    "venue_name": "林肯爵士乐上海中心",
    "venue_info": {
        "venue_address": "南京东路139号4层（近江西中路）",
        "lng": 121.486706,
        "lat": 31.238062
    },
    "project_info": "\n\n主题介绍:\n在一年四季中，我们知道春夏秋冬的变化，而对于爱情而言，也同样存在着四个独特的“季节”:相识、热恋、平淡和结束。我们将通过一系列不同的歌曲，深入探讨和演绎这四个爱情的季节。从初遇时的青涩与激动，到热恋中的炽热和浪漫，再到平淡生活中的深情与稳定，最终走向结束时的回忆与释怀，每一首歌曲都将带领您穿越爱情的不同阶段，感受其丰富的情感层次和深刻的心灵触动。这场音乐会不仅是对爱情四季的艺术化表达，更是一次关于人类情感的深刻探讨，让我们在歌曲的陪伴下，共同体验爱情的美丽与复杂。\n\n曲目单\n Location Unknown\nWhat a Difference Day Made\nTainted Love\nYour Heart is as Black as Night\nI am Me Once More\n恋爱俘虏\n离快乐再近一点\nFever\nDie with u\nThey Ought Write a Song\nYou Don‘t Know What Love is\nDanger in Loving You\nDesafinado\n实际曲目以现场为准\n\n乐队介绍:\n“Sleepless 不眠”是一支来自于上海的爵士乐队,由(键盘)刘力为，(贝斯)李曜宇，(歌手)周语菡，(鼓)朱欣冬组成。\n“Slpeeless”不完全局限于爵士,因为我们希望可以在音乐上做更多元化的表达,所以也涉及到 Pop，Bossanova，以及原创系列的歌曲团队内乐手和歌手均有四年以上乐龄，并且有丰富的舞台经验，分别毕业于上海音乐学院以及上海戏剧学院，专业性极强，乐队成员均参加过“OkOk Club~上海国际艺术节…“林肯爵士中心”等知名舞台,且拥有独特的音乐见解与表现力。\n \nVocal：Zita周语菡\n周语菡，是上海戏剧学院现代音乐表演专业的学生，以其卓越的歌唱天赋和艺术才华广为人知。 从十七岁起，她就深入研究声乐演唱，并于后来考入上海戏剧学院，专攻流行声乐。\n她的磁性女中音具有独特的辨识度，擅长演绎多种风格，包括流行、爵士和r&b\n曾获得2019年上海戏剧学院校园歌手大赛亚军，并积极参与浓情静安 · 爵士春天系列音乐会\n自2020年起，在“Blue  note  Shanghai”和 “OkOk     Club”等知名爵士俱乐部短期演出，展现了她的\n多才多艺。\n同时，她还是Bilibili和小红书的音乐博主，通过网络平台与观众分享她的音乐和艺术见解。\n2021年，她发布了网易云个人原创单曲《Champs Elysees》和《离快乐再近一点》,受到了广泛的 好评和关注。\n自2021年起，她开始系统学习爵士演唱，并积极参与上海国际艺术节、林肯爵士中心等活动，与 各路歌手和乐队合作演出，不断挑战自我，展现艺术的无限可能。\n此外，她还兼职担任小众服饰品牌“EMME”   的模特，并在2022年拍摄了饰品品牌“ALP Jewelry” 的广告，展现了她的多面艺术魅力。\n \nBass：李曜宇 Liby\n爵士贝斯手，自幼学习音乐，包括贝 斯与吉他演奏，2022年来到上海，\n师从爵士贝斯演奏家Joseph han学   习爵士演奏理念，师从爵士贝斯演奏 家教育家闵艺学习演奏技巧，接受包 俊睿、et徐广君、梁颖等指导，音乐 上擅长传统爵士、Funk、Fusion等\n多种风格的演奏，深受Paul\n神秘之光、阿乱五重奏等乐队贝斯    手，曾于此凯迪拉克上海音乐厅参与 演出王悆三重奏并参与官方宣传片拍 摄，参与kumato新疆巡演并参与乌   鲁木齐广播电视台快乐直通车录制，  参与有趣的新疆青年拍摄，活跃于    JZ club、林肯爵士乐中心，House   of Blues and Jazz，上海音乐厅，\n东方艺术中心，梅奔音乐俱乐部等上 海一线爵士舞台。\n \nDrums:朱欣冬\n从小随父亲学习爵士鼓，2021年以爵士鼓专业第一名的成绩\n考入上海音乐学院跟随褚伟明老师学习。在2016年曾获得全国鼓手大 奏预备青年组冠军，2017年随左声道乐队获晚安国际樱花\n节冠军并与迪玛希同台演出，2017—2019年随湖南爱乐乐团在长沙音 乐厅、湖南大剧院、中南大学、湖南农业大学、湖南师范大学\n等地演出，曾受邀Joy人声乐团参加湖南青年文化艺术节演出，曾受长 沙特警队邀请作为打击乐手于长沙人民会堂演出，多次在上音歌剧院、 贺厅、JzClub、Jzlive等地演出，2022参加加拿大国际音乐大赛获得第 一名，俄罗斯国际大赛获得第二名。\n \nKeys：韩旭\n青年爵士钢琴家 ，爵士作曲家 ，爵士大乐队编曲者，上海视觉艺术学院流行器乐专业教师 ，毕业于上海  音乐学院爵士钢琴专业，获硕士学位 。上海星漫沃克音乐文化发展有限公司创始人之一，同时担任于 Rj jazz bigband 、 The Seven Countrymen 、神秘之光爵士三重奏 、Star Walker 钢琴手及乐队作曲 。\n2015 年以专业  全国第一名考入南京艺术学院学习古典钢琴， 师从于旅俄博士孙铿亮副教授 。在校期间多次表演原创钢琴作品并举  办个人独奏音乐会，多次获得古典钢琴类的比赛奖项 。2018 年开始接触爵士并系统学习爵士演奏，2019 年以专业  第一名考入上海音乐学院爵士钢琴专业攻读硕士，师从于中国爵士钢琴家贺乐副教授，多次参与贺乐音乐工作室“爵  妙黑白 ”系列爵士独奏 、爵士双钢琴 、小乐队等多种类型音乐会 。\n2020 年起跟随安德利教授学习研究爵士作曲，期\n2020 年起跟随安德利教授学习研究爵士作曲，期  间活跃于上海各大著名爵士舞台，并在 2020 年 10 月加入上海 Rj 爵士大乐团担任钢琴手 。\n个人原创爵士代表作有： 《 Mysterious Man》、《 Fly me to the place where you are》 等， 已在多处表演并获得一致好评 。2022 年加入  天伦爱乐即兴钢琴演奏家研习会成为创会会员 。九月担任上海国际学校光华中学爵士电声乐队课程的外聘教师 。曾  被法国著名爵士钢琴大师 Serge Forte 赞扬:“在创作与改编上有着很好的技巧和美妙的和声编配功底 ”。2023 年组  建“神秘之光爵士三重奏 ”以及“The Seven Countrymen ”爵士乐队活跃于育音堂 、House of blues jazz 等地  演出 ，2023 年 9 月起担任上海视觉艺术学院流行音乐舞蹈学院流行器乐专业教师 。\n \nFeature Trumpet：邹子昊\n青年爵士小号手、 中国音协爵士乐学会会 员。2023 年毕业于上海音乐学院，获得本 科学士学位 。 师从上海音乐学院爵士小号 副教授、研究生导师、著名爵士小号演奏家 李晓川教授。自幼学习小号、长笛，2019 年 以全系专业总分第一考入上海音乐学院现 打系爵士专业。曾获 2020 年德国波恩贝多 芬“优秀演奏家大奖赛 ” 国际音乐比赛一等 奖、2021 年加拿大国际音乐比赛大学专业 爵士组第三名等多个国际爵士奖项 。活跃 于 Jz Club 、 BlueNote、林肯上海爵士乐中 心等著名爵士舞台。曾受邀参与 2022 上海\n国际音乐剧节巅峰演唱会、法国“JUAN”国际爵士音乐节等。曾多次参与电影音乐 配乐与专辑音乐录制，如：北京国际电影节最佳影片《云霄之上》小号配音等项 目。\n \n",
    "project_imgs": [
        "https://img.alicdn.com/bao/uploaded/i2/2251059038/O1CN014CBcrs2GdSfrW2QaX_!!4611686018427383646-2-item_pic.png",
        "https://img.alicdn.com/imgextra/i4/2251059038/O1CN01EMzylH2GdSfptDar2_!!2251059038.jpg",
        "https://img.alicdn.com/imgextra/i2/2251059038/O1CN01aSmJPI2GdSfrTrA08_!!2251059038.jpg",
        "https://img.alicdn.com/imgextra/i1/2251059038/O1CN01GSNCdL2GdSfpz2BKp_!!2251059038.jpg",
        "https://img.alicdn.com/imgextra/i1/2251059038/O1CN01ug9aVA2GdSfs2kIuK_!!2251059038.jpg",
        "https://img.alicdn.com/imgextra/i2/2251059038/O1CN01WD1ILR2GdSfpz4GLe_!!2251059038.jpg"
    ],
    "wantVO": {
        "wantNum": null,
        "wantNumStr": null,
        "wantNumSuffix": "人",
        "wantDesc": null
    },
    "tours": [],
    "project_link": "https://detail.damai.cn/item.htm?id=884641392953"
}