{
    "platform": "大麦",
    "project_id": "888226687064",
    "project_name": "4.17 Rowan Pattison Trio-2025中国巡演•上海站",
    "category_name": "演唱会",
    "artists": [],
    "show_status": "售票中",
    "show_time": "2025.04.17 周四 19:30",
    "session_time": [],
    "price": "168-298",
    "isGeneralAgent": "true",
    "isHotProject": "false",
    "rating": null,
    "city_name": "上海",
    "venue_name": "林肯爵士乐上海中心",
    "venue_info": {
        "venue_address": "南京东路139号4层（近江西中路）",
        "lng": 121.486706,
        "lat": 31.238062
    },
    "project_info": "\n澳大利亚最炙手可热的吉他手之一——Rowan Pattison将携带他的三重奏乐队在中国巡演，演奏他即将发行的新专辑作品以及其他经典爵士曲目。专辑灵感来源于 Aaron Parks、Mike Stern 以及澳大利亚和英国的爵士乐，将于2025年3月发布。这将是Rowan首次携该项目巡演中国。\n \n曲目单\nSet 1\n\nYou Must Believe in Spring\n作曲家: Michel Legrand\n \nDienda\n作曲家: Kenny Kirkland\n \nDetour Ahead\n作曲家: Herb Ellis\n \nTime Remembered\n作曲家: Bill Evans\n \nBells and Whistles\n作曲家: Rowan Pattison\n \nSet 2\nLifelike\n作曲家: Rowan Pattison\n \nWhen She Loved Me (From Disney’s Toy Story)\n作曲家: Randy Newman\n \nLviv\n作曲家: Rowan Pattison\n \nChengdu\n作曲家: Rowan Pattison\n实际演出曲目以现场为准\n\n \n演出阵容\nRowan Pattison- Guitar\n澳大利亚最受欢迎的爵士和当代吉他手之一，活跃于澳大利亚及国际音乐圈，参与众多的演出项目。他曾为 Shannen James、Jaron Jay、Mike Pensini 的 Organ Trio（曾与Ronan Keating、Tina Arena等合作）、Darryn Farrugia Project 和著名的 Jazzlab Orchestra 担任吉他手。此外，Rowan 获得了伦敦皇家音乐学院的硕士奖学金，并作为录音音乐人参与过 Cody Simpson、Paul Dempsy、Lee Bradshaw、Ruva Ngwenya、Nic Rouleau、Diana Huey 等人的作品，也曾参与 ABC Jazz、澳大利亚巡演的《Grease》、《9to5》、《Bring it On》等多个演出项目。Rowan 曾两次携手百老汇的知名艺人巡演中国。\n \nHadyn Murtagh- Bass\n澳大利亚最受欢迎的贝斯手之一，定期与传奇爵士钢琴家Bob Sedegreen和著名爵士吉他手Rowan Pattison合作演出。在他的职业生涯中，曾与众多备受尊敬的艺术家合作过，包括《出租车之旅》（Taxi Ride）、Darryn Faruggia、The Cat Empire、Mike Pensini、Ronan Keating、Tony Pantano、Julie O'Hara、John McCall以及墨尔本交响乐团合唱团。他还为Linda Taylor、Rowan Pattison、以及许多游戏音乐作曲家录制了众多专辑。他曾在世界上一些最著名的场馆演出，包括纽波特爵士音乐节（Newport Jazz Festival）、哈默大厅（Hamer Hall），以及澳大利亚和欧洲的许多爵士俱乐部，并在克莱蒙特学院（Claremont College）教授音乐课程。\n \nLu Ding吕鼎- Drums\n青年爵士鼓手\nDRUM—OFF 青年合作艺术家\n本科毕业于武汉音乐学院爵士鼓专业，师从任汉丁老师学习爵士鼓演奏、旅美爵士音乐家孙康宁老师、聂鑫老师学习爵士乐演奏、合奏与即兴理论，在校期间曾入选武汉音乐学院第一层次拔尖创新人才计划并多次举办爵士个人专场音乐会。现跟随著名爵士鼓演奏家徐之曈老师、旅法爵士钢琴家阿欣老师，韩国贝斯演奏家朴钟文老师学习节奏组的爵士演奏。\n曾在武汉创办多所爵士乐俱乐部，并长年活跃于华中地区各大爵士舞台以及知名音乐厅。如武汉琴台音乐厅、柏斯高天艺术家音乐中心、帕克爵士乐中心等等，曾与音乐歌手Domonique Paton(美国) 、Payson Lewis(美国）、Whitney Kaufman(美国)Andrew Johnson(美国）等合作，与中国著名室内乐团共同参演迪士尼·梦与希望100周年全球巡回中国地区的演出。\n在爵士乐领域中不断探索各种可能性和声音，并尝试在自己的音乐中融入了东方的元素。曾与众多一线爵士音乐家同台演出，如Viviana Zarbo 、黄韵、Emma艾玛、李伟乐、王艺霖、彭俊杰、朱泽旭、罗漠芃、胡宁、李敬、张卓然、黄兆永等。\n",
    "project_imgs": [
        "https://img.alicdn.com/bao/uploaded/i4/2251059038/O1CN014SKoOY2GdSfxeyGDw_!!4611686018427383646-2-item_pic.png",
        "https://img.alicdn.com/imgextra/i1/2251059038/O1CN01Qs4djl2GdSfzK6Nv7_!!2251059038.png",
        "https://img.alicdn.com/imgextra/i1/2251059038/O1CN01iqvr4w2GdSfxWfEAZ_!!2251059038.png",
        "https://img.alicdn.com/imgextra/i3/2251059038/O1CN01of5nAY2GdSfxyTula_!!2251059038.png"
    ],
    "wantVO": {
        "wantNum": null,
        "wantNumStr": null,
        "wantNumSuffix": "人",
        "wantDesc": null
    },
    "tours": [],
    "project_link": "https://detail.damai.cn/item.htm?id=888226687064"
}