{
    "platform": "大麦",
    "project_id": "889412911567",
    "project_name": "3.29「KPOPBOOM长沙站·新春特辑」室内KPOP狂欢音乐节",
    "category_name": "演唱会",
    "artists": [],
    "show_status": "售票中",
    "show_time": "2025.03.29 周六 20:00",
    "session_time": [],
    "price": "88-188",
    "isGeneralAgent": "true",
    "isHotProject": "false",
    "rating": null,
    "city_name": "长沙",
    "venue_name": "长沙VOX LIVEHOUSE",
    "venue_info": {
        "venue_address": "湖南省长沙市岳麓区天顶街道环湖路1200号梅溪湖国际文化艺术中心小剧场101号地下一层",
        "lng": 112.905414,
        "lat": 28.195744
    },
    "project_info": "【璀璨闪耀呈现】KPOP超级派对3.0——长沙站\n带上你的应援棒，我们现场见！\n*主办方享有音响文件的使用权利",
    "project_imgs": [
        "https://img.alicdn.com/bao/uploaded/i4/2251059038/O1CN01zwVTtF2GdSg3YMw34_!!4611686018427383646-2-item_pic.png",
        "https://img.alicdn.com/imgextra/i4/2251059038/O1CN01PhqjsZ2GdSg25paoj_!!2251059038.jpg"
    ],
    "wantVO": {
        "wantNum": null,
        "wantNumStr": null,
        "wantNumSuffix": "人",
        "wantDesc": null
    },
    "tours": [],
    "project_link": "https://detail.damai.cn/item.htm?id=889412911567"
}