{
    "platform": "大麦",
    "project_id": "898130937261",
    "project_name": "「MOSH！」2.0 Life Awaits×SOFARSOGOOD恰好 联合双专场",
    "category_name": "演唱会",
    "artists": [],
    "show_status": "售票中",
    "show_time": "2025.04.20 周日 20:00",
    "session_time": [],
    "price": "128",
    "isGeneralAgent": "false",
    "isHotProject": "false",
    "rating": null,
    "city_name": "佛山",
    "venue_name": "ALSO LIVE",
    "venue_info": {
        "venue_address": "怡和路6号ALSO(C座2层)",
        "lng": 113.222632,
        "lat": 22.933802
    },
    "project_info": "",
    "project_imgs": [
        "https://img.alicdn.com/bao/uploaded/i2/2251059038/O1CN01tZNqrw2GdSgPAhTAj_!!4611686018427383646-2-item_pic.png",
        "https://img.alicdn.com/imgextra/i1/2251059038/O1CN01R3QKHI2GdSgNfYbl1_!!2251059038.png",
        "https://img.alicdn.com/imgextra/i2/2251059038/O1CN01PlhKjU2GdSgNi7f8y_!!2251059038.jpg"
    ],
    "wantVO": {
        "wantNum": null,
        "wantNumStr": null,
        "wantNumSuffix": "人",
        "wantDesc": null
    },
    "tours": [],
    "project_link": "https://detail.damai.cn/item.htm?id=898130937261"
}