{
    "platform": "猫眼",
    "project_id": "198650",
    "project_name": "飞狗诚献-再见乌托邦",
    "category_name": "演唱会",
    "artists": [],
    "show_status": "演出延期中",
    "show_time": "2022.3.16 20:00 周三",
    "session_time": [],
    "price": "90-160",
    "isGeneralAgent": "false",
    "isHotProject": "false",
    "rating": null,
    "city_name": "北京",
    "venue_name": "MAOlivehouse-五棵松店",
    "venue_info": {
        "venue_address": "复兴路69号华熙LIVEhi-up广场B1层",
        "lng": "116.277331",
        "lat": "39.910025"
    },
    "project_info": "",
    "project_imgs": [
        "https://p0.meituan.net/myvideodistribute/f64e1b35a33baae5abc9a77e5915ed381876232.png",
        "https://p0.meituan.net/myvideodistribute/f64e1b35a33baae5abc9a77e5915ed381876232.png?w=1080&h=1680"
    ],
    "wantVO": {
        "wantNum": null,
        "wantNumStr": null,
        "wantNumSuffix": null,
        "wantDesc": null
    },
    "tours": [],
    "project_link": "https://www.gewara.com/detail/198650"
}