{
    "platform": "猫眼",
    "project_id": "259775",
    "project_name": "【周日亲子场】爱丽丝迷迭梦境—兔子洞歌舞晚宴绮梦之旅",
    "category_name": "演唱会",
    "artists": [],
    "show_status": "售票中",
    "show_time": "2024.5.26 13:00 周日",
    "session_time": [],
    "price": "150-200",
    "isGeneralAgent": "false",
    "isHotProject": "false",
    "rating": null,
    "city_name": "上海",
    "venue_name": "THE PEARL livehouse 珍珠剧场-上海",
    "venue_info": {
        "venue_address": "乍浦路471号",
        "lng": "121.486185",
        "lat": "31.252105"
    },
    "project_info": "",
    "project_imgs": [
        "https://p0.meituan.net/myvideodistribute/852ddcd7d8688f6b06569a2c1f44ac12321563.jpg",
        "https://p0.meituan.net/myvideodistribute/71b0f037f5ba1e52b1fc7609846fed172276433.jpg?w=1600&h=7220",
        "https://p1.meituan.net/myvideodistribute/a0a0d2574fe3733aaa0287488a84db5b1366193.jpg?w=1600&h=4140",
        "https://p0.meituan.net/myvideodistribute/c38aa9dbd504f7c9c5bc5b3df7421c2a1995444.jpg?w=1600&h=7280",
        "https://p0.meituan.net/myvideodistribute/b3a59885b4e9847aac3f472a79e8f1712785800.jpg?w=1600&h=15320",
        "https://p0.meituan.net/myvideodistribute/3521fcb1393024e50390772dc502dbcb160931.jpg?w=640&h=614"
    ],
    "wantVO": {
        "wantNum": null,
        "wantNumStr": null,
        "wantNumSuffix": null,
        "wantDesc": null
    },
    "tours": [],
    "project_link": "https://www.gewara.com/detail/259775"
}